docs/source/conf.py
getdist/__init__.py
getdist/_base.py
getdist/analysis_defaults.ini
getdist/arviz_wrapper.py
getdist/chain_grid.py
getdist/chains.py
getdist/cobaya_interface.py
getdist/command_line.py
getdist/convolve.py
getdist/covcomb.py
getdist/covmat.py
getdist/covscale.py
getdist/densities.py
getdist/distparam_template.ini
getdist/gaussian_mixtures.py
getdist/inifile.py
getdist/kde_bandwidth.py
getdist/matplotlib_ext.py
getdist/mcsamples.py
getdist/paramnames.py
getdist/parampriors.py
getdist/plots.py
getdist/types.py
getdist/yaml_tools.py
getdist/gui/SyntaxHighlight.py
getdist/gui/__init__.py
getdist/gui/mainwindow.py
getdist/gui/streamlit_app.py
getdist/gui/images/GetDistGUI.icns
getdist/gui/images/Icon.png
getdist/styles/__init__.py
getdist/styles/planck.paramnames
getdist/styles/planck.py
getdist/styles/sfmath.sty
getdist/styles/tab10.py
getdist/tests/__init__.py
getdist/tests/getdist_test.py
getdist/tests/test_arviz_wrapper.py
getdist/tests/test_distributions.py
getdist-1.7.2.dist-info/licenses/LICENCE.txt
scripts/build_mac_app.py
scripts/build_windows_app.py
scripts/create_windows_msi.py
scripts/multiprocessing_hook.py
scripts/run_plot_gallery.py
scripts/sign_windows_app.py
getdist-1.7.2.dist-info/METADATA
getdist-1.7.2.dist-info/WHEEL
getdist-1.7.2.dist-info/entry_points.txt
getdist-1.7.2.dist-info/top_level.txt
getdist-1.7.2.dist-info/RECORD
