Metadata-Version: 2.4
Name: getdist
Version: 1.7.2
Summary: GetDist Monte Carlo sample analysis, plotting and GUI
Author: Antony Lewis
License-Expression: LGPL-3.0-or-later
Project-URL: Homepage, https://getdist.readthedocs.io
Project-URL: Documentation, https://getdist.readthedocs.io
Project-URL: Source, https://github.com/cmbant/getdist
Project-URL: Tracker, https://github.com/cmbant/getdist/issues
Project-URL: Licensing, https://github.com/cmbant/getdist/blob/master/LICENCE.txt
Keywords: MCMC,KDE,sample,density estimation,plot,figure
Platform: any
Classifier: Development Status :: 5 - Production/Stable
Classifier: Operating System :: OS Independent
Classifier: Environment :: Console
Classifier: Intended Audience :: Science/Research
Classifier: Topic :: Scientific/Engineering :: Astronomy
Classifier: Programming Language :: Python :: 3.10
Classifier: Programming Language :: Python :: 3.11
Classifier: Programming Language :: Python :: 3.12
Classifier: Programming Language :: Python :: 3.13
Requires-Python: >=3.10.0
License-File: LICENCE.txt
Requires-Dist: numpy>=1.23.0
Requires-Dist: matplotlib!=3.5.0,>=2.2.0
Requires-Dist: scipy>=1.5
Requires-Dist: PyYAML>=5.1
Requires-Dist: packaging>=24
Provides-Extra: gui
Requires-Dist: PySide6>=6.1; extra == "gui"
Provides-Extra: streamlitgui
Requires-Dist: streamlit>=1.24.0; extra == "streamlitgui"
Provides-Extra: docs
Requires-Dist: sphinx; extra == "docs"
Requires-Dist: sphinx_rtd_theme>=1.0; extra == "docs"
Requires-Dist: sphinxcontrib-jquery; extra == "docs"
Requires-Dist: sphinx_markdown_builder; extra == "docs"
Requires-Dist: jupytext; extra == "docs"
Dynamic: license-file
